smps/__init__.py
smps/fit.py
smps/io.py
smps/models.py
smps/plots.py
smps/rcmod.py
smps/utils.py
py_smps-2.0.0.dist-info/LICENSE
py_smps-2.0.0.dist-info/WHEEL
py_smps-2.0.0.dist-info/METADATA
py_smps-2.0.0.dist-info/RECORD
