Metadata-Version: 2.1
Name: py-smps
Version: 2.0.0
Summary: A simple python library to import and visualize data from particle sizing instruments.
Home-page: https://github.com/quant-aq/py-smps
License: MIT
Author: David H Hagan
Author-email: david.hagan@quant-aq.com
Requires-Python: >=3.7.1,<4.0.0
Classifier: License :: OSI Approved :: MIT License
Classifier: Programming Language :: Python :: 3
Classifier: Programming Language :: Python :: 3.8
Classifier: Programming Language :: Python :: 3.9
Requires-Dist: joblib (>=1.0.0,<2.0.0)
Requires-Dist: numpy (>=1.19.1,<2.0.0)
Requires-Dist: pandas (>=1.2.4,<2.0.0)
Requires-Dist: requests (>=2.24.0,<3.0.0)
Requires-Dist: scipy (>=1.5.2,<2.0.0)
Requires-Dist: seaborn (>=0.10.1,<0.11.0)
Requires-Dist: statsmodels (>=0.12.0,<0.13.0)
Project-URL: Repository, https://github.com/quant-aq/py-smps
